axonemalyze/__init__.py
axonemalyze/estimate_circularity.py
axonemalyze/segment_axonemes.py
axonemalyze-0.0.2.dist-info/METADATA
axonemalyze-0.0.2.dist-info/WHEEL
axonemalyze-0.0.2.dist-info/entry_points.txt
axonemalyze-0.0.2.dist-info/licenses/LICENSE
axonemalyze-0.0.2.dist-info/RECORD
