Metadata-Version: 2.4
Name: axonemalyze
Version: 0.0.2
Summary: Calculate the circularity of axoneme picks from cryo-ET images.
Project-URL: repository, https://github.com/ammsa23/axonemalyze
Author-email: Ammaar Saeed <ammaar_saeed@g.harvard.edu>
License: MIT License
License-File: LICENSE
Classifier: Development Status :: 3 - Alpha
Classifier: License :: OSI Approved :: MIT License
Classifier: Natural Language :: English
Classifier: Operating System :: OS Independent
Classifier: Programming Language :: Python :: 3
Classifier: Typing :: Typed
Requires-Python: >=3.7
Requires-Dist: numpy
Requires-Dist: pandas
Requires-Dist: scipy
Provides-Extra: dev
Requires-Dist: black; extra == 'dev'
Requires-Dist: pandas; extra == 'dev'
Requires-Dist: pytest; extra == 'dev'
Requires-Dist: pytest-cov; extra == 'dev'
Provides-Extra: test
Requires-Dist: numpy; extra == 'test'
Requires-Dist: pytest-cov; extra == 'test'
Requires-Dist: pytest>=6.0; extra == 'test'
Requires-Dist: scipy; extra == 'test'
